omfvista/__init__.py
omfvista/lineset.py
omfvista/pointset.py
omfvista/surface.py
omfvista/utilities.py
omfvista/volume.py
omfvista/wrapper.py
tests/__init__.py
tests/element_test.py
tests/project_test.py
omfvista-0.3.1.dist-info/LICENSE
omfvista-0.3.1.dist-info/METADATA
omfvista-0.3.1.dist-info/WHEEL
omfvista-0.3.1.dist-info/top_level.txt
omfvista-0.3.1.dist-info/RECORD
