Metadata-Version: 2.1
Name: omfvista
Version: 0.3.1
Summary: 3D visualization for the Open Mining Format (omf)
Home-page: https://github.com/OpenGeoVis/omfvista
Author: Bane Sullivan
Author-email: info@pvgeo.org
License: UNKNOWN
Platform: UNKNOWN
Classifier: Programming Language :: Python
Classifier: License :: OSI Approved :: BSD License
Classifier: Operating System :: OS Independent
Classifier: Natural Language :: English
Requires-Dist: omf>=1.0.0
Requires-Dist: vectormath>=0.2.2
Requires-Dist: pyvista>=0.20.1
Requires-Dist: numpy
Requires-Dist: matplotlib
